coverage2img/__init__.py
coverage2img/coverage2img.py
coverage2img/coverage_model.py
coverage2img/main.py
coverage2img-0.0.1rc2.dist-info/LICENSE
coverage2img-0.0.1rc2.dist-info/METADATA
coverage2img-0.0.1rc2.dist-info/WHEEL
coverage2img-0.0.1rc2.dist-info/entry_points.txt
coverage2img-0.0.1rc2.dist-info/top_level.txt
coverage2img-0.0.1rc2.dist-info/RECORD
